[
  {
    "id": 1,
    "nombre": "Cocteleria Acrilico",
    "categoria": "Bazar, Cocteleria y Botanicos",
    "img": "/images/bazar-cocteleria-botanicos/coctelera-acrilico-con-medidor.png"
  },
  {
    "id": 2,
    "nombre": "Coctelera Boston",
    "categoria": "Bazar, Cocteleria y Botanicos",
    "img": "/images/bazar-cocteleria-botanicos/coctelera-boston.png"
  },
  {
    "id": 3,
    "nombre": "Coctelera Plástica",
    "categoria": "Bazar, Cocteleria y Botanicos",
    "img": "/images/bazar-cocteleria-botanicos/coctelera-plastica-con-medidor.png"
  },
  {
    "id": 4,
    "nombre": "Colador Oruga",
    "categoria": "Bazar, Cocteleria y Botanicos",
    "img": "/images/bazar-cocteleria-botanicos/colador-oruga.png"
  },
  {
    "id": 5,
    "nombre": "Copa Andes",
    "categoria": "Bazar, Cocteleria y Botanicos",
    "img": "/images/bazar-cocteleria-botanicos/copa-andes.png"
  },
  {
    "id": 6,
    "nombre": "Copa Aperol Spritz",
    "categoria": "Bazar, Cocteleria y Botanicos",
    "img": "/images/bazar-cocteleria-botanicos/copa-aperol-spiritz.png"
  },
  {
    "id": 7,
    "nombre": "Copa Martini",
    "categoria": "Bazar, Cocteleria y Botanicos",
    "img": "/images/bazar-cocteleria-botanicos/copa-martini.png"
  },
  {
    "id": 8,
    "nombre": "Cuchara Espiral Negra",
    "categoria": "Bazar, Cocteleria y Botanicos",
    "img": "/images/bazar-cocteleria-botanicos/cuchara-espiral-negra.png"
  },
  {
    "id": 9,
    "nombre": "Delantal Stella con latas",
    "categoria": "Bazar, Cocteleria y Botanicos",
    "img": "/images/bazar-cocteleria-botanicos/delantal-stella-con-latas.png"
  },
  {
    "id": 10,
    "nombre": "Esterilla Jagermeister",
    "categoria": "Bazar, Cocteleria y Botanicos",
    "img": "/images/bazar-cocteleria-botanicos/esterilla-jagermeister.png"
  },
  {
    "id": 11,
    "nombre": "Frapera Acero",
    "categoria": "Bazar, Cocteleria y Botanicos",
    "img": "/images/bazar-cocteleria-botanicos/frapera-acero.png"
  },
  {
    "id": 12,
    "nombre": "Iconos Botánicos",
    "categoria": "Bazar, Cocteleria y Botanicos",
    "img": "/images/bazar-cocteleria-botanicos/iconos-botanicos.png"
  },
  {
    "id": 13,
    "nombre": "Jigger Medidor",
    "categoria": "Bazar, Cocteleria y Botanicos",
    "img": "/images/bazar-cocteleria-botanicos/jigger-medidor.png"
  },
  {
    "id": 14,
    "nombre": "Libro Set Vino",
    "categoria": "Bazar, Cocteleria y Botanicos",
    "img": "/images/bazar-cocteleria-botanicos/libro-set-vino.png"
  },
  {
    "id": 15,
    "nombre": "Palo Mortero de Acero",
    "categoria": "Bazar, Cocteleria y Botanicos",
    "img": "/images/bazar-cocteleria-botanicos/palo-mortero-de-acero.png"
  },
  {
    "id": 16,
    "nombre": "Pinza Precision",
    "categoria": "Bazar, Cocteleria y Botanicos",
    "img": "/images/bazar-cocteleria-botanicos/pinza-precision.png"
  },
  {
    "id": 17,
    "nombre": "Vaso Jack Daniels",
    "categoria": "Bazar, Cocteleria y Botanicos",
    "img": "/images/bazar-cocteleria-botanicos/vaso-jack-daniels.png"
  },
  {
    "id": 18,
    "nombre": "Vaso Redondo Cerveza",
    "categoria": "Bazar, Cocteleria y Botanicos",
    "img": "/images/bazar-cocteleria-botanicos/vaso-redondo-cerveza.png"
  },
  {
    "id": 19,
    "nombre": "Vaso Shot",
    "categoria": "Bazar, Cocteleria y Botanicos",
    "img": "/images/bazar-cocteleria-botanicos/vaso-shot.png"
  },
  {
    "id": 20,
    "nombre": "Vaso Warsteiner",
    "categoria": "Bazar, Cocteleria y Botanicos",
    "img": "/images/bazar-cocteleria-botanicos/vaso-warsteiner.png"
  },
  {
    "id": 21,
    "nombre": "Vaso Whisky",
    "categoria": "Bazar, Cocteleria y Botanicos",
    "img": "/images/bazar-cocteleria-botanicos/vaso-whisky.png"
  },
  {
    "id": 22,
    "nombre": "Amarula",
    "categoria": "Bebidas Destiladas",
    "img": "/images/bebidas-destiladas/amarula.png"
  },
  {
    "id": 24,
    "nombre": "Baileys",
    "categoria": "Bebidas Destiladas",
    "img": "/images/bebidas-destiladas/baileys.png"
  },
  {
    "id": 25,
    "nombre": "Barcelo Dorado",
    "categoria": "Bebidas Destiladas",
    "img": "/images/bebidas-destiladas/barcelo-dorado.png"
  },
  {
    "id": 26,
    "nombre": "Beefeater",
    "categoria": "Bebidas Destiladas",
    "img": "/images/bebidas-destiladas/beefeater.png"
  },
  {
    "id": 27,
    "nombre": "Campari Rosso",
    "categoria": "Bebidas Destiladas",
    "img": "/images/bebidas-destiladas/campari-rosso.png"
  },
  {
    "id": 28,
    "nombre": "Carpano Rosso",
    "categoria": "Bebidas Destiladas",
    "img": "/images/bebidas-destiladas/carpano-rosso.png"
  },
  {
    "id": 29,
    "nombre": "Frizze",
    "categoria": "Bebidas Destiladas",
    "img": "/images/bebidas-destiladas/frizze.png"
  },
  {
    "id": 30,
    "nombre": "Gancia",
    "categoria": "Bebidas Destiladas",
    "img": "/images/bebidas-destiladas/gancia.png"
  },
  {
    "id": 31,
    "nombre": "Granadina Cusenier",
    "categoria": "Bebidas Destiladas",
    "img": "/images/bebidas-destiladas/granadina-cusenier.png"
  },
  {
    "id": 32,
    "nombre": "Hesperidina",
    "categoria": "Bebidas Destiladas",
    "img": "/images/bebidas-destiladas/hesperidina.png"
  },
  {
    "id": 33,
    "nombre": "Jack Daniels Honey",
    "categoria": "Bebidas Destiladas",
    "img": "/images/bebidas-destiladas/jack-daniels-honey.png"
  },
  {
    "id": 34,
    "nombre": "Jagermeister",
    "categoria": "Bebidas Destiladas",
    "img": "/images/bebidas-destiladas/jagermeister.png"
  },
  {
    "id": 35,
    "nombre": "Jameson Ipa",
    "categoria": "Bebidas Destiladas",
    "img": "/images/bebidas-destiladas/jameson-ipa.png"
  },
  {
    "id": 36,
    "nombre": "Jim Beam Devils Cut",
    "categoria": "Bebidas Destiladas",
    "img": "/images/bebidas-destiladas/jim-beam-devils-cut.png"
  },
  {
    "id": 37,
    "nombre": "Llave",
    "categoria": "Bebidas Destiladas",
    "img": "/images/bebidas-destiladas/llave.png"
  },
  {
    "id": 38,
    "nombre": "Malibu",
    "categoria": "Bebidas Destiladas",
    "img": "/images/bebidas-destiladas/malibu.png"
  },
  {
    "id": 39,
    "nombre": "Martini",
    "categoria": "Bebidas Destiladas",
    "img": "/images/bebidas-destiladas/martini.png"
  },
  {
    "id": 40,
    "nombre": "Sidra Real",
    "categoria": "Bebidas Destiladas",
    "img": "/images/bebidas-destiladas/sidra-real.png"
  },
  {
    "id": 41,
    "nombre": "Skyy Vodka",
    "categoria": "Bebidas Destiladas",
    "img": "/images/bebidas-destiladas/sky-vodka.png"
  },
  {
    "id": 42,
    "nombre": "Tia Maria Cafe",
    "categoria": "Bebidas Destiladas",
    "img": "/images/bebidas-destiladas/tia-maria-cafe.png"
  },
  {
    "id": 43,
    "nombre": "ACDC Lata",
    "categoria": "Cervezas",
    "img": "/images/cervezas/acdc-lata.png"
  },
  {
    "id": 44,
    "nombre": "Brahma",
    "categoria": "Cervezas",
    "img": "/images/cervezas/brahma.png"
  },
  {
    "id": 45,
    "nombre": "Carlberg",
    "categoria": "Cervezas",
    "img": "/images/cervezas/carlberg.png"
  },
  {
    "id": 46,
    "nombre": "Corona Grande",
    "categoria": "Cervezas",
    "img": "/images/cervezas/corona-grande-descartable.png"
  },
  {
    "id": 47,
    "nombre": "Estrella Damm",
    "categoria": "Cervezas",
    "img": "/images/cervezas/estrella-damm-lata.png"
  },
  {
    "id": 48,
    "nombre": "Faxe Ipa",
    "categoria": "Cervezas",
    "img": "/images/cervezas/faxe-ipa-lata.png"
  },
  {
    "id": 49,
    "nombre": "Heineken",
    "categoria": "Cervezas",
    "img": "/images/cervezas/heineken.png"
  },
  {
    "id": 50,
    "nombre": "Isenbeck",
    "categoria": "Cervezas",
    "img": "/images/cervezas/isenbeck.png"
  },
  {
    "id": 51,
    "nombre": "Amstel Lager",
    "categoria": "Cervezas",
    "img": "/images/cervezas/lata-amstel-lager.png"
  },
  {
    "id": 52,
    "nombre": "Cordoba",
    "categoria": "Cervezas",
    "img": "/images/cervezas/lata-cordoba.png"
  },
  {
    "id": 53,
    "nombre": "Heineken Lata",
    "categoria": "Cervezas",
    "img": "/images/cervezas/lata-heineken.png"
  },
  {
    "id": 54,
    "nombre": "Warsteiner",
    "categoria": "Cervezas",
    "img": "/images/cervezas/lata-warsteiner.png"
  },
  {
    "id": 55,
    "nombre": "Miller",
    "categoria": "Cervezas",
    "img": "/images/cervezas/miller.png"
  },
  {
    "id": 56,
    "nombre": "Oranjeboom",
    "categoria": "Cervezas",
    "img": "/images/cervezas/oranjeboom.png"
  },
  {
    "id": 57,
    "nombre": "Patagonia Amber Lager",
    "categoria": "Cervezas",
    "img": "/images/cervezas/patagonia-amber-lager.png"
  },
  {
    "id": 58,
    "nombre": "Peñón Mexican Lager",
    "categoria": "Cervezas",
    "img": "/images/cervezas/penon-lata-mexican-lager.png"
  },
  {
    "id": 59,
    "nombre": "Quilmes",
    "categoria": "Cervezas",
    "img": "/images/cervezas/quilmes.png"
  },
  {
    "id": 60,
    "nombre": "Salta Rubia",
    "categoria": "Cervezas",
    "img": "/images/cervezas/salta-rubia.png"
  },
  {
    "id": 61,
    "nombre": "Schofferhofer",
    "categoria": "Cervezas",
    "img": "/images/cervezas/shofferhofer-pomelo.png"
  },
  {
    "id": 62,
    "nombre": "Cartas Jagermeister",
    "categoria": "Juegos Hangover",
    "img": "/images/juegos-hangover/cartas-jagermeister.png"
  },
  {
    "id": 63,
    "nombre": "Dardos",
    "categoria": "Juegos Hangover",
    "img": "/images/juegos-hangover/dardos.png"
  },
  {
    "id": 64,
    "nombre": "Ludo",
    "categoria": "Juegos Hangover",
    "img": "/images/juegos-hangover/ludo.png"
  },
  {
    "id": 65,
    "nombre": "Fútbol",
    "categoria": "Juegos Hangover",
    "img": "/images/juegos-hangover/futbol.png"
  },
  {
    "id": 66,
    "nombre": "Ruleta",
    "categoria": "Juegos Hangover",
    "img": "/images/juegos-hangover/ruleta.png"
  },
  {
    "id": 67,
    "nombre": "Spin",
    "categoria": "Juegos Hangover",
    "img": "/images/juegos-hangover/spin.png"
  },
  {
    "id": 68,
    "nombre": "Tateti",
    "categoria": "Juegos Hangover",
    "img": "/images/juegos-hangover/tateti.png"
  },
  {
    "id": 69,
    "nombre": "Dispenser",
    "categoria": "Juegos Hangover",
    "img": "/images/juegos-hangover/dispenser.png"
  },
  {
    "id": 70,
    "nombre": "Bondiola de Cerdo Vacío",
    "categoria": "Snacks",
    "img": "/images/snacks/bondiola-cerdo-vacio.png"
  },
  {
    "id": 71,
    "nombre": "Lomo de Cerdo Vacío",
    "categoria": "Snacks",
    "img": "/images/snacks/lomo-cerdo-vacio.png"
  },
  {
    "id": 72,
    "nombre": "Maní",
    "categoria": "Snacks",
    "img": "/images/snacks/mani.png"
  },
  {
    "id": 73,
    "nombre": "Papas Quento",
    "categoria": "Snacks",
    "img": "/images/snacks/papas-quento.png"
  },
  {
    "id": 74,
    "nombre": "Salame Bozzana Tira",
    "categoria": "Snacks",
    "img": "/images/snacks/salame-bozzana-tira.png"
  },
  {
    "id": 75,
    "nombre": "Salame Bozzana Vacío",
    "categoria": "Snacks",
    "img": "/images/snacks/salame-bozzana-vacio.png"
  },
  {
    "id": 76,
    "nombre": "Aristides Varietales",
    "categoria": "Vinos y Espumantes",
    "img": "/images/vinos-espumantes/aristides-varietales.png"
  },
  {
    "id": 77,
    "nombre": "Benjamin Malbec",
    "categoria": "Vinos y Espumantes",
    "img": "/images/vinos-espumantes/benjamin-malbec.png"
  },
  {
    "id": 78,
    "nombre": "Capriccio Fiore",
    "categoria": "Vinos y Espumantes",
    "img": "/images/vinos-espumantes/capriccio-fiore.png"
  },
  {
    "id": 79,
    "nombre": "Chandon Extra Brut",
    "categoria": "Vinos y Espumantes",
    "img": "/images/vinos-espumantes/chandon-extra-brut.png"
  },
  {
    "id": 80,
    "nombre": "Dada Espumante",
    "categoria": "Vinos y Espumantes",
    "img": "/images/vinos-espumantes/dada-espumante.png"
  },
  {
    "id": 81,
    "nombre": "Dilema Blanco Dulce",
    "categoria": "Vinos y Espumantes",
    "img": "/images/vinos-espumantes/dilema-blanco-dulce.png"
  },
  {
    "id": 82,
    "nombre": "Domador del Desierto",
    "categoria": "Vinos y Espumantes",
    "img": "/images/vinos-espumantes/domador-del-desierto.png"
  },
  {
    "id": 83,
    "nombre": "Doña Paula Rose",
    "categoria": "Vinos y Espumantes",
    "img": "/images/vinos-espumantes/dona-paula-rose.png"
  },
  {
    "id": 84,
    "nombre": "El Abuelo Oporto",
    "categoria": "Vinos y Espumantes",
    "img": "/images/vinos-espumantes/el-abuelo-oporto.png"
  },
  {
    "id": 85,
    "nombre": "El Esteco Blend",
    "categoria": "Vinos y Espumantes",
    "img": "/images/vinos-espumantes/el-esteco-blend.png"
  },
  {
    "id": 86,
    "nombre": "La Linda Extra Brut",
    "categoria": "Vinos y Espumantes",
    "img": "/images/vinos-espumantes/la-linda-extra-brut.png"
  },
  {
    "id": 87,
    "nombre": "Mosquita Muerta",
    "categoria": "Vinos y Espumantes",
    "img": "/images/vinos-espumantes/mosquita-muerta.png"
  },
  {
    "id": 88,
    "nombre": "Mumm Extra Brut",
    "categoria": "Vinos y Espumantes",
    "img": "/images/vinos-espumantes/mumm-extra-brut.png"
  },
  {
    "id": 89,
    "nombre": "Oveja Negra",
    "categoria": "Vinos y Espumantes",
    "img": "/images/vinos-espumantes/oveja-negra.png"
  },
  {
    "id": 90,
    "nombre": "Perro Callejero",
    "categoria": "Vinos y Espumantes",
    "img": "/images/vinos-espumantes/perro-callejero.png"
  },
  {
    "id": 91,
    "nombre": "Quara Malbec",
    "categoria": "Vinos y Espumantes",
    "img": "/images/vinos-espumantes/quara-malbec.png"
  },
  {
    "id": 92,
    "nombre": "Santa Florentina Syrah",
    "categoria": "Vinos y Espumantes",
    "img": "/images/vinos-espumantes/santa-florentina-syrah.png"
  },
  {
    "id": 93,
    "nombre": "Siempre tengo un plan b",
    "categoria": "Vinos y Espumantes",
    "img": "/images/vinos-espumantes/siempre-tengo-un-plan-b.png"
  },
  {
    "id": 94,
    "nombre": "Signos Malbec",
    "categoria": "Vinos y Espumantes",
    "img": "/images/vinos-espumantes/signos-malbec.png"
  },
  {
    "id": 95,
    "nombre": "Trumpeter Malbec",
    "categoria": "Vinos y Espumantes",
    "img": "/images/vinos-espumantes/trumpeter-malbec.png"
  },
  {
    "id": 96,
    "nombre": "Otro Loco Más",
    "categoria": "Vinos y Espumantes",
    "img": "/images/vinos-espumantes/otro-loco-mas.png"
  }
]
